tinypng/__init__.py
tinypng/api.py
tinypng/cmd.py
tinypng/common.py
tinypng-3.0.0.dist-info/DESCRIPTION.rst
tinypng-3.0.0.dist-info/METADATA
tinypng-3.0.0.dist-info/RECORD
tinypng-3.0.0.dist-info/WHEEL
tinypng-3.0.0.dist-info/entry_points.txt
tinypng-3.0.0.dist-info/metadata.json
tinypng-3.0.0.dist-info/top_level.txt
