Metadata-Version: 2.0
Name: tinypng
Version: 3.0.0
Summary: Access api.tinypng.org from the shell and python scripts
Home-page: https://github.com/mbarkhau/tinypng/
Author: Manuel Barkhau
Author-email: mbarkhau@gmail.com
License: BSD License
Keywords: p,n,g, ,i,m,a,g,e, ,c,o,m,p,r,e,s,s,i,o,n, ,t,i,n,y,p,n,g, ,s,h,r,i,n,k, ,j,p,e,g, ,j,p,g
Platform: UNKNOWN
Classifier: Development Status :: 4 - Beta
Classifier: Environment :: Console
Classifier: Environment :: Web Environment
Classifier: Intended Audience :: Developers
Classifier: License :: OSI Approved :: BSD License
Classifier: Operating System :: MacOS :: MacOS X
Classifier: Operating System :: POSIX
Classifier: Programming Language :: Python
Classifier: Programming Language :: Python :: 2
Classifier: Programming Language :: Python :: 3
Classifier: Topic :: Utilities
Requires-Dist: docopt (>=0.6)
Requires-Dist: requests (>=2.0)
Provides-Extra: dev
Requires-Dist: pytest; extra == 'dev'
Requires-Dist: wheel; extra == 'dev'
